MANIFEST.in
README
__init__.py
__pkginfo__.py
entities.py
schema.py
setup.py
views.py
cubicweb_mailinglist.egg-info/PKG-INFO
cubicweb_mailinglist.egg-info/SOURCES.txt
cubicweb_mailinglist.egg-info/dependency_links.txt
cubicweb_mailinglist.egg-info/requires.txt
cubicweb_mailinglist.egg-info/top_level.txt
i18n/en.po
i18n/fr.po
migration/1.7.1_Any.py
migration/postcreate.py
test/test_mailinglist.py