Metadata-Version: 1.0
Name: cubicweb-mailinglist
Version: 1.7.3
Summary: mailing-list component for the CubicWeb framework
Home-page: http://www.cubicweb.org/project/cubicweb-mailinglist
Author: Logilab
Author-email: contact@logilab.fr
License: LGPL
Platform: UNKNOWN
